dist/ka_uts_eviq-5.0.1.250630-py3-none-any.whl
dist/ka_uts_eviq-5.0.1.250630.tar.gz
docs/Makefile
docs/conf.py
docs/index.rst
docs/make.bat
docs/requirements.txt
ka_uts_eviq/__init__.py
ka_uts_eviq/__version__.py
ka_uts_eviq/py.typed
ka_uts_eviq/xls/__init__.py
ka_uts_eviq/xls/cfg.py
ka_uts_eviq/xls/taskin.py
ka_uts_eviq/xls/taskioc.py
ka_uts_eviq/xls/utils.py
ka_uts_eviq/xls/verify.py
ka_uts_eviq/xls/docs/conf.py
ka_uts_eviq/xls/docs/index.rst
ka_uts_eviq/xls/docs/make.bat
ka_uts_eviq-5.0.1.20250702.dist-info/licenses/LICENSE.txt
ka_uts_eviq-5.0.1.20250702.dist-info/METADATA
ka_uts_eviq-5.0.1.20250702.dist-info/WHEEL
ka_uts_eviq-5.0.1.20250702.dist-info/top_level.txt
ka_uts_eviq-5.0.1.20250702.dist-info/RECORD
