Metadata-Version: 2.4
Name: ka_uts_eviq
Version: 5.0.1.20250702
Summary: Utilities for EcoVadis IQ  Processing
Author-email: Bernd Stroehle <bernd.stroehle@gmail.com>
Maintainer-email: Bernd Stroehle <bernd.stroehle@gmail.com>
License-Expression: MIT AND (Apache-2.0 OR BSD-2-Clause)
Project-URL: Source Code, https://github.com/bs2910/ka_uts_eviq/tree/master
Project-URL: Homepage, https://kosakya.de/
Project-URL: Documentation, https://ka_uts_eviq.readthedocs.io/en/latest
Project-URL: Apache-2.0 License, https://apache.org/licenses/LICENSE-2.0
Project-URL: GPLv3 License, https://www.gnu.org/licenses/gpl-3.0.en.html
Classifier: Development Status :: 5 - Production/Stable
Classifier: Intended Audience :: Developers
Classifier: Operating System :: OS Independent
Classifier: Programming Language :: Python :: 3.10
Classifier: Natural Language :: English
Classifier: Topic :: Software Development :: Libraries :: Python Modules
Requires-Python: >=3.11
License-File: LICENSE.txt
Requires-Dist: geopy>=2.4.1
Requires-Dist: ka_uts_aod>=4.1.0.250525
Requires-Dist: ka_uts_dfr>=4.1.2.250609
Requires-Dist: ka_uts_dic>=4.1.2.250612
Requires-Dist: ka_uts_log>=4.1.1.250609
Requires-Dist: ka_uts_path>=5.0.0.250623
Requires-Dist: ka_uts_xls>=4.1.1.250620
Requires-Dist: numpy>=2.3.1
Requires-Dist: openpyxl>=3.1.5
Requires-Dist: pandas>=2.3.0
Requires-Dist: postal_codes_tools>=1.1.3
Requires-Dist: pycountry>=24.6.1
Requires-Dist: python-calamine>=0.3.1
Dynamic: license-file
